gtfs_flex_to_gofs/__init__.py
gtfs_flex_to_gofs/__main__.py
gtfs_flex_to_gofs/default_headers.py
gtfs_flex_to_gofs/gofs_converter.py
gtfs_flex_to_gofs/gofs_data.py
gtfs_flex_to_gofs/gofs_file.py
gtfs_flex_to_gofs/patch_gtfs.py
gtfs_flex_to_gofs/utils.py
gtfs_flex_to_gofs/files/__init__.py
gtfs_flex_to_gofs/files/booking_rules.py
gtfs_flex_to_gofs/files/calendars.py
gtfs_flex_to_gofs/files/fares.py
gtfs_flex_to_gofs/files/gofs.py
gtfs_flex_to_gofs/files/gofs_versions.py
gtfs_flex_to_gofs/files/operation_rules.py
gtfs_flex_to_gofs/files/service_brands.py
gtfs_flex_to_gofs/files/system_information.py
gtfs_flex_to_gofs/files/vehicle_types.py
gtfs_flex_to_gofs/files/wait_time.py
gtfs_flex_to_gofs/files/wait_times.py
gtfs_flex_to_gofs/files/zones.py
gtfs_flex_to_gofs-0.5.2.dist-info/licenses/LICENSE
gtfs_flex_to_gofs-0.5.2.dist-info/METADATA
gtfs_flex_to_gofs-0.5.2.dist-info/WHEEL
gtfs_flex_to_gofs-0.5.2.dist-info/entry_points.txt
gtfs_flex_to_gofs-0.5.2.dist-info/top_level.txt
gtfs_flex_to_gofs-0.5.2.dist-info/RECORD
