Metadata-Version: 2.4
Name: GTFS-flex-to-GOFS
Version: 0.5.2
Summary: Convert GTFS Flex to GOFS
Author: Nicholas Paun, Jonathan Milot
License: MIT
Project-URL: Homepage, https://github.com/TransitApp/GTFS-flex-to-GOFS
Project-URL: Repository, https://github.com/TransitApp/GTFS-flex-to-GOFS
Classifier: License :: OSI Approved :: MIT License
Classifier: Programming Language :: Python :: 3
Requires-Python: >=3.10
License-File: LICENSE
Requires-Dist: py-gtfs-loader>=0.3.1
Requires-Dist: shapely>=2.0.4
Provides-Extra: dev
Requires-Dist: pytest; extra == "dev"
Requires-Dist: flake8; extra == "dev"
Dynamic: license-file
